languagechange/__init__.py
languagechange/languagechange.py
languagechange-0.4.0.dist-info/METADATA
languagechange-0.4.0.dist-info/WHEEL
languagechange-0.4.0.dist-info/RECORD
