Metadata-Version: 2.3
Name: languagechange
Version: 0.4.0
Summary: 
Author: atossa
Author-email: atossa@xerxeslabs.com
Requires-Python: >=3.9,<4.0
Classifier: Programming Language :: Python :: 3
Classifier: Programming Language :: Python :: 3.9
Classifier: Programming Language :: Python :: 3.10
Classifier: Programming Language :: Python :: 3.11
Classifier: Programming Language :: Python :: 3.12
Classifier: Programming Language :: Python :: 3.13
Requires-Dist: pytest (>=8.3.5,<9.0.0)
Requires-Dist: typer (>=0.15.2,<0.16.0)
